cvm/__init__.py
cvm/_version.py
cvm/exceptions.py
cvm/utils.py
cvm/balances/__init__.py
cvm/balances/account_layout.py
cvm/balances/balance_sheet.py
cvm/balances/income_statement.py
cvm/balances/common/__init__.py
cvm/balances/common/dre.py
cvm/balances/financial/__init__.py
cvm/balances/financial/bpa.py
cvm/balances/financial/bpp.py
cvm/balances/financial/cvm_codes.py
cvm/balances/financial/dre.py
cvm/balances/industrial/__init__.py
cvm/balances/industrial/bpa.py
cvm/balances/industrial/bpp.py
cvm/balances/industrial/cvm_codes.py
cvm/balances/industrial/dre.py
cvm/balances/insurance/__init__.py
cvm/balances/insurance/bpa.py
cvm/balances/insurance/bpp.py
cvm/balances/insurance/cvm_codes.py
cvm/balances/insurance/dre.py
cvm/cad/__init__.py
cvm/cad/company.py
cvm/csvio/__init__.py
cvm/csvio/batch.py
cvm/csvio/dfpitr.py
cvm/csvio/document.py
cvm/csvio/fca.py
cvm/csvio/fre.py
cvm/csvio/member.py
cvm/csvio/row.py
cvm/datatypes/__init__.py
cvm/datatypes/account.py
cvm/datatypes/address.py
cvm/datatypes/auditor.py
cvm/datatypes/bookkeeping_agent.py
cvm/datatypes/capital_distribution.py
cvm/datatypes/communication_channel.py
cvm/datatypes/contact.py
cvm/datatypes/controlling_interest.py
cvm/datatypes/currency.py
cvm/datatypes/document.py
cvm/datatypes/industry.py
cvm/datatypes/investor_relations.py
cvm/datatypes/issuer.py
cvm/datatypes/phone.py
cvm/datatypes/registration.py
cvm/datatypes/security.py
cvm/datatypes/shareholder_department.py
cvm/datatypes/statement.py
cvm/datatypes/tax_id.py
cvm/datatypes/trading_admission.py
pycvm-0.4.1.dist-info/LICENSE
pycvm-0.4.1.dist-info/METADATA
pycvm-0.4.1.dist-info/WHEEL
pycvm-0.4.1.dist-info/top_level.txt
pycvm-0.4.1.dist-info/RECORD
