Metadata-Version: 2.1
Name: pycvm
Version: 0.4.1
Summary: Python library for processing data from CVM
Home-page: https://github.com/glourencoffee/pycvm/
Author: Giovanni Lourenço
Author-email: gvnl.developer@outlook.com
License: MIT
Keywords: investment,finances
Requires-Python: >=3.7
License-File: LICENSE
